fastapi_redis_cache/__init__.py
fastapi_redis_cache/cache.py
fastapi_redis_cache/client.py
fastapi_redis_cache/enums.py
fastapi_redis_cache/key_gen.py
fastapi_redis_cache/redis.py
fastapi_redis_cache/types.py
fastapi_redis_cache/util.py
fastapi_redis_cache/version.py
fastapi_redis_cache_hakiergrzonzo-0.2.6.dist-info/LICENSE
fastapi_redis_cache_hakiergrzonzo-0.2.6.dist-info/METADATA
fastapi_redis_cache_hakiergrzonzo-0.2.6.dist-info/WHEEL
fastapi_redis_cache_hakiergrzonzo-0.2.6.dist-info/top_level.txt
fastapi_redis_cache_hakiergrzonzo-0.2.6.dist-info/RECORD
