Metadata-Version: 2.1
Name: fastapi-redis-cache-hakiergrzonzo
Version: 0.2.6
Summary: A patch to the simple and robust caching solution for FastAPI endpoints, fueled by the unfathomable power of Redis. Fixes the support for pydantic models.
Home-page: https://github.com/hakiergrzonzo/fastapi-redis-cache
Author: Aaron Luna + Grzegorz Koperwas
Author-email: admin@grzegorzkoperwas.site
Maintainer: Aaron Luna + Grzegorz Koperwas
Maintainer-email: admin@grzegorzkoperwas.site
License: MIT
Project-URL: Bug Tracker, https://github.com/hakiergrzonzo/fastapi-redis-cache/issues
Project-URL: Source Code, https://github.com/hakiergrzonzo/fastapi-redis-cache
Platform: UNKNOWN
Classifier: Development Status :: 4 - Beta
Classifier: Intended Audience :: Developers
Classifier: License :: OSI Approved :: MIT License
Classifier: Natural Language :: English
Classifier: Operating System :: MacOS :: MacOS X
Classifier: Operating System :: POSIX :: Linux
Classifier: Operating System :: Unix
Classifier: Programming Language :: Python :: 3.7
Classifier: Programming Language :: Python :: 3.8
Classifier: Programming Language :: Python :: 3.9
Classifier: Programming Language :: Python :: 3 :: Only
Requires-Python: >=3.7
License-File: LICENSE
Requires-Dist: fastapi
Requires-Dist: pydantic
Requires-Dist: python-dateutil
Requires-Dist: redis
Provides-Extra: dev
Requires-Dist: black ; extra == 'dev'
Requires-Dist: coverage ; extra == 'dev'
Requires-Dist: fakeredis ; extra == 'dev'
Requires-Dist: flake8 ; extra == 'dev'
Requires-Dist: isort ; extra == 'dev'
Requires-Dist: pytest ; extra == 'dev'
Requires-Dist: pytest-cov ; extra == 'dev'
Requires-Dist: pytest-flake8 ; extra == 'dev'
Requires-Dist: pytest-random-order ; extra == 'dev'
Requires-Dist: requests ; extra == 'dev'
